invoice_details_lib/__init__.py
invoice_details_lib/invoice_details.py
invoice_details_lib-0.1.0.dist-info/licenses/LICENSE
invoice_details_lib-0.1.0.dist-info/METADATA
invoice_details_lib-0.1.0.dist-info/WHEEL
invoice_details_lib-0.1.0.dist-info/top_level.txt
invoice_details_lib-0.1.0.dist-info/RECORD
