Metadata-Version: 2.4
Name: invoice_details_lib
Version: 0.1.0
Summary: A Python library for creating the invoice transaction code and transaction date
Author-email: Gopi Chand <x23335912@student.ncirl.ie>
License: MIT
Keywords: invoice
Classifier: Development Status :: 3 - Alpha
Classifier: Intended Audience :: Education
Classifier: License :: OSI Approved :: MIT License
Classifier: Operating System :: Microsoft :: Windows :: Windows 10
Classifier: Programming Language :: Python :: 3.9
Classifier: Programming Language :: Python :: 3.10
Classifier: Programming Language :: Python :: 3.11
Requires-Python: >=3.6
License-File: LICENSE
Requires-Dist: Pillow>=10.0.0
Dynamic: license-file
